[{"__type__":"cc.SpriteFrame","content":{"name":"select","texture":"1d51ad986","rect":[3,3,150,81],"offset":[0,0],"originalSize":[150,81],"rotated":1,"capInsets":[0,0,0,0]}},[{"__type__":"cc.Prefab","_name":"BetTitleNode","data":{"__id__":1}},{"__type__":"cc.Node","_name":"TypeNode","_children":[{"__id__":2},{"__id__":4},{"__id__":6}],"_components":[{"__type__":"cc.Toggle","node":{"__id__":1},"_N$target":{"__id__":1},"_N$isChecked":false,"checkMark":{"__id__":3},"checkEvents":[{"__type__":"cc.ClickEvent","target":{"__id__":1},"_componentId":"7bcdb63+MVGkILFUznaySxk","handler":"onclick"}]},{"__type__":"7bcdb63+MVGkILFUznaySxk","node":{"__id__":1},"typeName":{"__id__":5}}],"_prefab":{"__type__":"cc.PrefabInfo","root":{"__id__":1},"asset":{"__uuid__":"3bQo6v7BVOqoTWhMMgaPz1"},"fileId":"35w4cfcTRLea+/hCK9gx7K"},"_contentSize":{"__type__":"cc.Size","width":300,"height":162},"_trs":{"__type__":"TypedArray","ctor":"Float64Array","array":[150,0,0,0,0,0,1,1,1,1]}},{"__type__":"cc.Node","_name":"checkmark","_parent":{"__id__":1},"_active":false,"_components":[{"__id__":3}],"_prefab":{"__type__":"cc.PrefabInfo","root":{"__id__":1},"asset":{"__uuid__":"3bQo6v7BVOqoTWhMMgaPz1"},"fileId":"7cnzKuVsVG4KkcRCDs5CZC"},"_contentSize":{"__type__":"cc.Size","width":300,"height":162},"_trs":{"__type__":"TypedArray","ctor":"Float64Array","array":[0,0,0,0,0,0,1,1,1,1]}},{"__type__":"cc.Sprite","node":{"__id__":2},"_materials":[{"__uuid__":"ecpdLyjvZBwrvm+cedCcQy"}],"_spriteFrame":{"__uuid__":"2ev5pgdW1JEbsQfKbNznaz"},"_type":1,"_sizeMode":2},{"__type__":"cc.Node","_name":"title_lab","_parent":{"__id__":1},"_components":[{"__id__":5}],"_prefab":{"__type__":"cc.PrefabInfo","root":{"__id__":1},"asset":{"__uuid__":"3bQo6v7BVOqoTWhMMgaPz1"},"fileId":"a5OFvSsKdFAZNxGJKnpIWA"},"_color":{"__type__":"cc.Color","r":255,"g":244,"b":234},"_contentSize":{"__type__":"cc.Size","width":200,"height":44},"_trs":{"__type__":"TypedArray","ctor":"Float64Array","array":[0,27.021,0,0,0,0,1,1,1,1]}},{"__type__":"cc.Label","node":{"__id__":4},"_materials":[{"__uuid__":"ecpdLyjvZBwrvm+cedCcQy"}],"_useOriginalSize":false,"_fontSize":44,"_lineHeight":44,"_N$horizontalAlign":1,"_N$verticalAlign":1,"_N$overflow":2},{"__type__":"cc.Node","_name":"name_lab","_parent":{"__id__":1},"_components":[{"__type__":"cc.Label","node":{"__id__":6},"_materials":[{"__uuid__":"ecpdLyjvZBwrvm+cedCcQy"}],"_useOriginalSize":false,"_string":"投注记录","_N$string":"投注记录","_fontSize":46,"_lineHeight":46,"_N$horizontalAlign":1,"_N$verticalAlign":1,"_N$overflow":2}],"_prefab":{"__type__":"cc.PrefabInfo","root":{"__id__":1},"asset":{"__uuid__":"3bQo6v7BVOqoTWhMMgaPz1"},"fileId":"595tZZcY9JL65rls5Lakva"},"_color":{"__type__":"cc.Color","r":255,"g":244,"b":234},"_contentSize":{"__type__":"cc.Size","width":200,"height":42},"_trs":{"__type__":"TypedArray","ctor":"Float64Array","array":[0,-24.236,0,0,0,0,1,1,1,1]}}],{"__type__":"cc.SpriteFrame","content":{"name":"singleColor","texture":"a8Anh32NZGRZegUtSgEj26","rect":[0,0,2,2],"offset":[0,0],"originalSize":[2,2],"capInsets":[0,0,0,0]}},{"__type__":"cc.SpriteFrame","content":{"name":"bet_title_img","texture":"1d51ad986","rect":[3,400,40,40],"offset":[0,0],"originalSize":[40,40],"capInsets":[14,15,14,10]}},[{"__type__":"cc.Prefab","_name":"BetRecordPlane","data":{"__id__":1}},{"__type__":"cc.Node","_name":"BetRecordPlane","_children":[{"__id__":2},{"__id__":8},{"__id__":12},{"__id__":19}],"_components":[{"__type__":"34bedzKGa9EF6IpSJuhmFS/","node":{"__id__":1},"title_content":{"__id__":11},"betScroll":{"__id__":7},"info_content":{"__id__":4},"titlePrefab":{"__uuid__":"3bQo6v7BVOqoTWhMMgaPz1"},"noInfoSign":{"__id__":6},"pageSize":16},{"__type__":"bd281EfomBBsJdBjiCU5XcL","node":{"__id__":1},"itemPrefab":{"__uuid__":"68nXXj3yBE26xBU/Ei0BdI"},"scrollViewNode":{"__id__":2},"contentNode":{"__id__":4},"initItemCount":16,"scriptName":"BetInfoItem","bufferZone":800,"itemInterval":120,"currentMode":1},{"__type__":"cc.Widget","node":{"__id__":1},"alignMode":2,"_alignFlags":45,"_originalWidth":1672,"_originalHeight":1060}],"_prefab":{"__type__":"cc.PrefabInfo","root":{"__id__":1},"asset":{"__uuid__":"b0vDWc0FpBrqXtpimJc21n"},"fileId":"66sd9ZlMpBZYZOmQjxiBBP"},"_contentSize":{"__type__":"cc.Size","width":2208,"height":1242},"_trs":{"__type__":"TypedArray","ctor":"Float64Array","array":[1104,621,0,0,0,0,1,1,1,1]}},{"__type__":"cc.Node","_name":"New ScrollView","_parent":{"__id__":1},"_children":[{"__id__":3},{"__id__":5}],"_components":[{"__id__":7},{"__type__":"cc.Widget","node":{"__id__":2},"_alignFlags":45,"_top":352,"_bottom":14.349000000000004,"_originalWidth":1672,"_originalHeight":800}],"_prefab":{"__type__":"cc.PrefabInfo","root":{"__id__":1},"asset":{"__uuid__":"b0vDWc0FpBrqXtpimJc21n"},"fileId":"a6JPa7OmlIZbEwIeUWLOIP"},"_contentSize":{"__type__":"cc.Size","width":2208,"height":875.651},"_trs":{"__type__":"TypedArray","ctor":"Float64Array","array":[0,-168.82549999999998,0,0,0,0,1,1,1,1]}},{"__type__":"cc.Node","_name":"view","_parent":{"__id__":2},"_children":[{"__id__":4}],"_components":[{"__type__":"cc.Mask","node":{"__id__":3},"_materials":[{"__uuid__":"ecpdLyjvZBwrvm+cedCcQy"}],"_N$alphaThreshold":0},{"__type__":"cc.Widget","node":{"__id__":3},"_alignFlags":45,"_originalWidth":1672,"_originalHeight":800}],"_prefab":{"__type__":"cc.PrefabInfo","root":{"__id__":1},"asset":{"__uuid__":"b0vDWc0FpBrqXtpimJc21n"},"fileId":"8aF7ISTihOn464bppuZ/fs"},"_contentSize":{"__type__":"cc.Size","width":2208,"height":875.651},"_trs":{"__type__":"TypedArray","ctor":"Float64Array","array":[0,0,0,0,0,0,1,1,1,1]}},{"__type__":"cc.Node","_name":"content","_parent":{"__id__":3},"_components":[{"__type__":"cc.Widget","node":{"__id__":4},"_alignFlags":41,"_originalWidth":1672}],"_prefab":{"__type__":"cc.PrefabInfo","root":{"__id__":1},"asset":{"__uuid__":"b0vDWc0FpBrqXtpimJc21n"},"fileId":"f6RqD2kiBI+ZbtehQ8oAFS"},"_contentSize":{"__type__":"cc.Size","width":2208,"height":120},"_anchorPoint":{"__type__":"cc.Vec2","x":0.5,"y":1},"_trs":{"__type__":"TypedArray","ctor":"Float64Array","array":[0,437.8255,0,0,0,0,1,1,1,1]}},{"__type__":"cc.Node","_name":"noInfo","_parent":{"__id__":2},"_active":false,"_components":[{"__id__":6}],"_prefab":{"__type__":"cc.PrefabInfo","root":{"__id__":1},"asset":{"__uuid__":"b0vDWc0FpBrqXtpimJc21n"},"fileId":"90H99Hq21GcJt+5GeU568R"},"_contentSize":{"__type__":"cc.Size","width":247,"height":265},"_trs":{"__type__":"TypedArray","ctor":"Float64Array","array":[0,0,0,0,0,0,1,1,1,1]}},{"__type__":"cc.Sprite","node":{"__id__":5},"_materials":[{"__uuid__":"ecpdLyjvZBwrvm+cedCcQy"}],"_spriteFrame":{"__uuid__":"bcinjr2UlINYJevEF8rbCe"}},{"__type__":"cc.ScrollView","node":{"__id__":2},"horizontal":false,"brake":0.75,"bounceDuration":0.23,"_N$content":{"__id__":4},"content":{"__id__":4},"_N$horizontalScrollBar":null,"_N$verticalScrollBar":null},{"__type__":"cc.Node","_name":"title_bg","_parent":{"__id__":1},"_children":[{"__id__":9}],"_components":[{"__type__":"cc.Sprite","node":{"__id__":8},"_materials":[{"__uuid__":"ecpdLyjvZBwrvm+cedCcQy"}],"_spriteFrame":{"__uuid__":"70DnKuzjdKEoAVgcOzyPkj"},"_type":1,"_sizeMode":0},{"__type__":"cc.Widget","node":{"__id__":8},"_alignFlags":41,"_originalWidth":1673}],"_prefab":{"__type__":"cc.PrefabInfo","root":{"__id__":1},"asset":{"__uuid__":"b0vDWc0FpBrqXtpimJc21n"},"fileId":"4cf5vi8wlBe7wRXxiF3Rg9"},"_contentSize":{"__type__":"cc.Size","width":2208,"height":166},"_trs":{"__type__":"TypedArray","ctor":"Float64Array","array":[0,538,0,0,0,0,1,1,1,1]}},{"__type__":"cc.Node","_name":"New ScrollView","_parent":{"__id__":8},"_children":[{"__id__":10}],"_components":[{"__type__":"cc.ScrollView","node":{"__id__":9},"vertical":false,"brake":0.75,"bounceDuration":0.23,"_N$content":{"__id__":11},"content":{"__id__":11},"_N$horizontalScrollBar":null,"_N$verticalScrollBar":null},{"__type__":"cc.Widget","node":{"__id__":9},"_alignFlags":41,"_originalWidth":1673}],"_prefab":{"__type__":"cc.PrefabInfo","root":{"__id__":1},"asset":{"__uuid__":"b0vDWc0FpBrqXtpimJc21n"},"fileId":"0cYV78zNpM7a5SAP0b1aUB"},"_contentSize":{"__type__":"cc.Size","width":2208,"height":166},"_trs":{"__type__":"TypedArray","ctor":"Float64Array","array":[0,0,0,0,0,0,1,1,1,1]}},{"__type__":"cc.Node","_name":"view","_parent":{"__id__":9},"_children":[{"__id__":11}],"_components":[{"__type__":"cc.Mask","node":{"__id__":10},"_materials":[{"__uuid__":"ecpdLyjvZBwrvm+cedCcQy"}],"_N$alphaThreshold":0},{"__type__":"cc.Widget","node":{"__id__":10},"_alignFlags":41,"_originalWidth":1673}],"_prefab":{"__type__":"cc.PrefabInfo","root":{"__id__":1},"asset":{"__uuid__":"b0vDWc0FpBrqXtpimJc21n"},"fileId":"11gmqHF15Bw66EzzvuPYgP"},"_contentSize":{"__type__":"cc.Size","width":2208,"height":166},"_trs":{"__type__":"TypedArray","ctor":"Float64Array","array":[0,0,0,0,0,0,1,1,1,1]}},{"__type__":"cc.Node","_name":"content","_parent":{"__id__":10},"_components":[{"__type__":"cc.Layout","node":{"__id__":11},"_layoutSize":{"__type__":"cc.Size","width":400,"height":166},"_resize":1,"_N$layoutType":1,"_N$spacingX":3},{"__type__":"cc.ToggleContainer","node":{"__id__":11}},{"__type__":"cc.Widget","node":{"__id__":11},"_alignFlags":41,"_right":1808,"_originalWidth":300}],"_prefab":{"__type__":"cc.PrefabInfo","root":{"__id__":1},"asset":{"__uuid__":"b0vDWc0FpBrqXtpimJc21n"},"fileId":"e6mHahOG5EraIzLFZHlXWt"},"_contentSize":{"__type__":"cc.Size","width":400,"height":166},"_anchorPoint":{"__type__":"cc.Vec2","y":0.5},"_trs":{"__type__":"TypedArray","ctor":"Float64Array","array":[-1104,0,0,0,0,0,1,1,1,1]}},{"__type__":"cc.Node","_name":"title_bg_2","_parent":{"__id__":1},"_children":[{"__id__":13}],"_components":[{"__type__":"cc.Sprite","node":{"__id__":12},"_materials":[{"__uuid__":"ecpdLyjvZBwrvm+cedCcQy"}],"_spriteFrame":{"__uuid__":"41D7kWhyFGY7q4NDlzkazn"},"_sizeMode":0},{"__type__":"cc.Widget","node":{"__id__":12},"alignMode":2,"_alignFlags":41,"_top":266,"_originalWidth":1673}],"_prefab":{"__type__":"cc.PrefabInfo","root":{"__id__":1},"asset":{"__uuid__":"b0vDWc0FpBrqXtpimJc21n"},"fileId":"2fGzmwI81OAJt/uK68EzYQ"},"_color":{"__type__":"cc.Color","r":69,"g":45,"b":22},"_contentSize":{"__type__":"cc.Size","width":2208,"height":86},"_trs":{"__type__":"TypedArray","ctor":"Float64Array","array":[0,312,0,0,0,0,1,1,1,1]}},{"__type__":"cc.Node","_name":"betTitle_labs","_parent":{"__id__":12},"_children":[{"__id__":14},{"__id__":15},{"__id__":16},{"__id__":17},{"__id__":18}],"_components":[{"__type__":"cc.Widget","node":{"__id__":13},"_alignFlags":40,"_top":106,"_bottom":-6,"_originalWidth":1673,"_originalHeight":100}],"_prefab":{"__type__":"cc.PrefabInfo","root":{"__id__":1},"asset":{"__uuid__":"b0vDWc0FpBrqXtpimJc21n"},"fileId":"e4NQm4FSFG7rgyaFpP+R3R"},"_contentSize":{"__type__":"cc.Size","width":2208,"height":86},"_trs":{"__type__":"TypedArray","ctor":"Float64Array","array":[0,0,0,0,0,0,1,1,1,1]}},{"__type__":"cc.Node","_name":"lab1","_parent":{"__id__":13},"_components":[{"__type__":"cc.Label","node":{"__id__":14},"_materials":[{"__uuid__":"ecpdLyjvZBwrvm+cedCcQy"}],"_useOriginalSize":false,"_string":"时间","_N$string":"时间","_fontSize":44,"_lineHeight":44,"_N$horizontalAlign":1,"_N$verticalAlign":1}],"_prefab":{"__type__":"cc.PrefabInfo","root":{"__id__":1},"asset":{"__uuid__":"b0vDWc0FpBrqXtpimJc21n"},"fileId":"faAKs9knFCGLU9KFBwYAaL"},"_color":{"__type__":"cc.Color","r":253,"g":210,"b":170},"_contentSize":{"__type__":"cc.Size","width":88,"height":55.44},"_trs":{"__type__":"TypedArray","ctor":"Float64Array","array":[-560,2,0,0,0,0,1,1,1,1]}},{"__type__":"cc.Node","_name":"lab2","_parent":{"__id__":13},"_components":[{"__type__":"cc.Label","node":{"__id__":15},"_materials":[{"__uuid__":"ecpdLyjvZBwrvm+cedCcQy"}],"_useOriginalSize":false,"_string":"笔数","_N$string":"笔数","_fontSize":44,"_lineHeight":44,"_N$horizontalAlign":1,"_N$verticalAlign":1}],"_prefab":{"__type__":"cc.PrefabInfo","root":{"__id__":1},"asset":{"__uuid__":"b0vDWc0FpBrqXtpimJc21n"},"fileId":"admreuBRdCj4rCT+/llw4Y"},"_color":{"__type__":"cc.Color","r":253,"g":210,"b":170},"_contentSize":{"__type__":"cc.Size","width":88,"height":55.44},"_trs":{"__type__":"TypedArray","ctor":"Float64Array","array":[-280,-1,0,0,0,0,1,1,1,1]}},{"__type__":"cc.Node","_name":"lab3","_parent":{"__id__":13},"_components":[{"__type__":"cc.Label","node":{"__id__":16},"_materials":[{"__uuid__":"ecpdLyjvZBwrvm+cedCcQy"}],"_useOriginalSize":false,"_string":"有效投注","_N$string":"有效投注","_fontSize":44,"_lineHeight":44,"_N$horizontalAlign":1,"_N$verticalAlign":1}],"_prefab":{"__type__":"cc.PrefabInfo","root":{"__id__":1},"asset":{"__uuid__":"b0vDWc0FpBrqXtpimJc21n"},"fileId":"edw2X/vghAc5IfNzd5pmup"},"_color":{"__type__":"cc.Color","r":253,"g":210,"b":170},"_contentSize":{"__type__":"cc.Size","width":176,"height":55.44},"_trs":{"__type__":"TypedArray","ctor":"Float64Array","array":[0,-1,0,0,0,0,1,1,1,1]}},{"__type__":"cc.Node","_name":"lab4","_parent":{"__id__":13},"_components":[{"__type__":"cc.Label","node":{"__id__":17},"_materials":[{"__uuid__":"ecpdLyjvZBwrvm+cedCcQy"}],"_useOriginalSize":false,"_string":"输赢","_N$string":"输赢","_fontSize":44,"_lineHeight":44,"_N$horizontalAlign":1,"_N$verticalAlign":1}],"_prefab":{"__type__":"cc.PrefabInfo","root":{"__id__":1},"asset":{"__uuid__":"b0vDWc0FpBrqXtpimJc21n"},"fileId":"cbyQEuwvJB/I8DoKFsD1lY"},"_color":{"__type__":"cc.Color","r":253,"g":210,"b":170},"_contentSize":{"__type__":"cc.Size","width":88,"height":55.44},"_trs":{"__type__":"TypedArray","ctor":"Float64Array","array":[280,-1,0,0,0,0,1,1,1,1]}},{"__type__":"cc.Node","_name":"lab5","_parent":{"__id__":13},"_components":[{"__type__":"cc.Label","node":{"__id__":18},"_materials":[{"__uuid__":"ecpdLyjvZBwrvm+cedCcQy"}],"_useOriginalSize":false,"_string":"注单","_N$string":"注单","_fontSize":44,"_lineHeight":44,"_N$horizontalAlign":1,"_N$verticalAlign":1}],"_prefab":{"__type__":"cc.PrefabInfo","root":{"__id__":1},"asset":{"__uuid__":"b0vDWc0FpBrqXtpimJc21n"},"fileId":"60wQc0HU9OLqU2PiMLgZFE"},"_color":{"__type__":"cc.Color","r":253,"g":210,"b":170},"_contentSize":{"__type__":"cc.Size","width":88,"height":55.44},"_trs":{"__type__":"TypedArray","ctor":"Float64Array","array":[560,-1,0,0,0,0,1,1,1,1]}},{"__type__":"cc.Node","_name":"title_bg_3","_parent":{"__id__":1},"_children":[{"__id__":20}],"_components":[{"__type__":"cc.Sprite","node":{"__id__":19},"_materials":[{"__uuid__":"ecpdLyjvZBwrvm+cedCcQy"}],"_spriteFrame":{"__uuid__":"beCxgXfiNCo7LNdLaFaL9J"},"_type":1,"_sizeMode":0},{"__type__":"cc.Widget","node":{"__id__":19},"alignMode":2,"_alignFlags":41,"_top":166,"_originalWidth":1673}],"_prefab":{"__type__":"cc.PrefabInfo","root":{"__id__":1},"asset":{"__uuid__":"b0vDWc0FpBrqXtpimJc21n"},"fileId":"0cAzAukYpNt7ew7JcanoWv"},"_contentSize":{"__type__":"cc.Size","width":2208,"height":100},"_trs":{"__type__":"TypedArray","ctor":"Float64Array","array":[0,405,0,0,0,0,1,1,1,1]}},{"__type__":"cc.Node","_name":"betTime","_parent":{"__id__":19},"_children":[{"__id__":21},{"__id__":25},{"__id__":29},{"__id__":33},{"__id__":37},{"__id__":41}],"_components":[{"__type__":"cc.Widget","node":{"__id__":20},"_alignFlags":45,"_originalWidth":500,"_originalHeight":80},{"__type__":"cc.ToggleContainer","node":{"__id__":20}},{"__type__":"cc.Layout","node":{"__id__":20},"_layoutSize":{"__type__":"cc.Size","width":2208,"height":100},"_resize":2,"_N$layoutType":1}],"_prefab":{"__type__":"cc.PrefabInfo","root":{"__id__":1},"asset":{"__uuid__":"b0vDWc0FpBrqXtpimJc21n"},"fileId":"53zMez8j9DGoQAgAMRx+7h"},"_contentSize":{"__type__":"cc.Size","width":2208,"height":100},"_trs":{"__type__":"TypedArray","ctor":"Float64Array","array":[0,0,0,0,0,0,1,1,1,1]}},{"__type__":"cc.Node","_name":"today","_parent":{"__id__":20},"_children":[{"__id__":22},{"__id__":24}],"_components":[{"__type__":"cc.Toggle","node":{"__id__":21},"checkMark":{"__id__":23},"checkEvents":[{"__type__":"cc.ClickEvent","target":{"__id__":1},"_componentId":"34bedzKGa9EF6IpSJuhmFS/","handler":"onClickTime","customEventData":"今天"}]}],"_prefab":{"__type__":"cc.PrefabInfo","root":{"__id__":1},"asset":{"__uuid__":"b0vDWc0FpBrqXtpimJc21n"},"fileId":"afYG18WNtMfJ+bmblNBZJn"},"_contentSize":{"__type__":"cc.Size","width":368,"height":99},"_trs":{"__type__":"TypedArray","ctor":"Float64Array","array":[-920,0,0,0,0,0,1,1,1,1]}},{"__type__":"cc.Node","_name":"bg","_parent":{"__id__":21},"_components":[{"__id__":23}],"_prefab":{"__type__":"cc.PrefabInfo","root":{"__id__":1},"asset":{"__uuid__":"b0vDWc0FpBrqXtpimJc21n"},"fileId":"f5BKf1rkdFeIsARfAlIaLT"},"_color":{"__type__":"cc.Color","r":156,"g":98,"b":41},"_contentSize":{"__type__":"cc.Size","width":250,"height":99},"_trs":{"__type__":"TypedArray","ctor":"Float64Array","array":[0,0,0,0,0,0,1,1,1,1]}},{"__type__":"cc.Sprite","node":{"__id__":22},"_materials":[{"__uuid__":"ecpdLyjvZBwrvm+cedCcQy"}],"_spriteFrame":{"__uuid__":"41D7kWhyFGY7q4NDlzkazn"},"_sizeMode":0},{"__type__":"cc.Node","_name":"lab","_parent":{"__id__":21},"_components":[{"__type__":"cc.Label","node":{"__id__":24},"_materials":[{"__uuid__":"ecpdLyjvZBwrvm+cedCcQy"}],"_useOriginalSize":false,"_string":"今天","_N$string":"今天","_fontSize":44,"_lineHeight":44,"_N$horizontalAlign":1,"_N$verticalAlign":1}],"_prefab":{"__type__":"cc.PrefabInfo","root":{"__id__":1},"asset":{"__uuid__":"b0vDWc0FpBrqXtpimJc21n"},"fileId":"b6qOLulNFAsZLrvyeCW+Lb"},"_color":{"__type__":"cc.Color","r":253,"g":210,"b":170},"_contentSize":{"__type__":"cc.Size","width":88,"height":55.44},"_trs":{"__type__":"TypedArray","ctor":"Float64Array","array":[0,0,0,0,0,0,1,1,1,1]}},{"__type__":"cc.Node","_name":"lastDay","_parent":{"__id__":20},"_children":[{"__id__":26},{"__id__":28}],"_components":[{"__type__":"cc.Toggle","node":{"__id__":25},"_N$isChecked":false,"checkMark":{"__id__":27},"checkEvents":[{"__type__":"cc.ClickEvent","target":{"__id__":1},"_componentId":"34bedzKGa9EF6IpSJuhmFS/","handler":"onClickTime","customEventData":"昨天"}]}],"_prefab":{"__type__":"cc.PrefabInfo","root":{"__id__":1},"asset":{"__uuid__":"b0vDWc0FpBrqXtpimJc21n"},"fileId":"f4h4YDOZlBk5DbTLAJMi/e"},"_contentSize":{"__type__":"cc.Size","width":368,"height":99},"_trs":{"__type__":"TypedArray","ctor":"Float64Array","array":[-552,0,0,0,0,0,1,1,1,1]}},{"__type__":"cc.Node","_name":"bg","_parent":{"__id__":25},"_active":false,"_components":[{"__id__":27}],"_prefab":{"__type__":"cc.PrefabInfo","root":{"__id__":1},"asset":{"__uuid__":"b0vDWc0FpBrqXtpimJc21n"},"fileId":"64EQ+euhNMK7b6gy8ZV/8p"},"_color":{"__type__":"cc.Color","r":156,"g":98,"b":41},"_contentSize":{"__type__":"cc.Size","width":250,"height":99},"_trs":{"__type__":"TypedArray","ctor":"Float64Array","array":[0,0,0,0,0,0,1,1,1,1]}},{"__type__":"cc.Sprite","node":{"__id__":26},"_materials":[{"__uuid__":"ecpdLyjvZBwrvm+cedCcQy"}],"_spriteFrame":{"__uuid__":"41D7kWhyFGY7q4NDlzkazn"},"_sizeMode":0},{"__type__":"cc.Node","_name":"lab","_parent":{"__id__":25},"_components":[{"__type__":"cc.Label","node":{"__id__":28},"_materials":[{"__uuid__":"ecpdLyjvZBwrvm+cedCcQy"}],"_useOriginalSize":false,"_string":"昨天","_N$string":"昨天","_fontSize":44,"_lineHeight":44,"_N$horizontalAlign":1,"_N$verticalAlign":1}],"_prefab":{"__type__":"cc.PrefabInfo","root":{"__id__":1},"asset":{"__uuid__":"b0vDWc0FpBrqXtpimJc21n"},"fileId":"33Gqf4PgVDwInjMcRLY+Fo"},"_color":{"__type__":"cc.Color","r":253,"g":210,"b":170},"_contentSize":{"__type__":"cc.Size","width":88,"height":55.44},"_trs":{"__type__":"TypedArray","ctor":"Float64Array","array":[0,0,0,0,0,0,1,1,1,1]}},{"__type__":"cc.Node","_name":"thisWeek","_parent":{"__id__":20},"_children":[{"__id__":30},{"__id__":32}],"_components":[{"__type__":"cc.Toggle","node":{"__id__":29},"_N$isChecked":false,"checkMark":{"__id__":31},"checkEvents":[{"__type__":"cc.ClickEvent","target":{"__id__":1},"_componentId":"34bedzKGa9EF6IpSJuhmFS/","handler":"onClickTime","customEventData":"本周"}]}],"_prefab":{"__type__":"cc.PrefabInfo","root":{"__id__":1},"asset":{"__uuid__":"b0vDWc0FpBrqXtpimJc21n"},"fileId":"70o5Kh0P1CHJ8F1t36ua9w"},"_contentSize":{"__type__":"cc.Size","width":368,"height":99},"_trs":{"__type__":"TypedArray","ctor":"Float64Array","array":[-184,0,0,0,0,0,1,1,1,1]}},{"__type__":"cc.Node","_name":"bg","_parent":{"__id__":29},"_active":false,"_components":[{"__id__":31}],"_prefab":{"__type__":"cc.PrefabInfo","root":{"__id__":1},"asset":{"__uuid__":"b0vDWc0FpBrqXtpimJc21n"},"fileId":"49N0+ep1pEwrdP0eWy2Vkd"},"_color":{"__type__":"cc.Color","r":156,"g":98,"b":41},"_contentSize":{"__type__":"cc.Size","width":250,"height":99},"_trs":{"__type__":"TypedArray","ctor":"Float64Array","array":[0,0,0,0,0,0,1,1,1,1]}},{"__type__":"cc.Sprite","node":{"__id__":30},"_materials":[{"__uuid__":"ecpdLyjvZBwrvm+cedCcQy"}],"_spriteFrame":{"__uuid__":"41D7kWhyFGY7q4NDlzkazn"},"_sizeMode":0},{"__type__":"cc.Node","_name":"lab","_parent":{"__id__":29},"_components":[{"__type__":"cc.Label","node":{"__id__":32},"_materials":[{"__uuid__":"ecpdLyjvZBwrvm+cedCcQy"}],"_useOriginalSize":false,"_string":"本周","_N$string":"本周","_fontSize":44,"_lineHeight":44,"_N$horizontalAlign":1,"_N$verticalAlign":1}],"_prefab":{"__type__":"cc.PrefabInfo","root":{"__id__":1},"asset":{"__uuid__":"b0vDWc0FpBrqXtpimJc21n"},"fileId":"0cRBRM7LxD9YdCjPP+r6yl"},"_color":{"__type__":"cc.Color","r":253,"g":210,"b":170},"_contentSize":{"__type__":"cc.Size","width":88,"height":55.44},"_trs":{"__type__":"TypedArray","ctor":"Float64Array","array":[0,0,0,0,0,0,1,1,1,1]}},{"__type__":"cc.Node","_name":"lastWeek","_parent":{"__id__":20},"_children":[{"__id__":34},{"__id__":36}],"_components":[{"__type__":"cc.Toggle","node":{"__id__":33},"_N$isChecked":false,"checkMark":{"__id__":35},"checkEvents":[{"__type__":"cc.ClickEvent","target":{"__id__":1},"_componentId":"34bedzKGa9EF6IpSJuhmFS/","handler":"onClickTime","customEventData":"上周"}]}],"_prefab":{"__type__":"cc.PrefabInfo","root":{"__id__":1},"asset":{"__uuid__":"b0vDWc0FpBrqXtpimJc21n"},"fileId":"8b83D+yOFNhrDeL6EOJIEs"},"_contentSize":{"__type__":"cc.Size","width":368,"height":99},"_trs":{"__type__":"TypedArray","ctor":"Float64Array","array":[184,0,0,0,0,0,1,1,1,1]}},{"__type__":"cc.Node","_name":"bg","_parent":{"__id__":33},"_active":false,"_components":[{"__id__":35}],"_prefab":{"__type__":"cc.PrefabInfo","root":{"__id__":1},"asset":{"__uuid__":"b0vDWc0FpBrqXtpimJc21n"},"fileId":"29Bf8CIGBJ/LdsS2CpnJGb"},"_color":{"__type__":"cc.Color","r":156,"g":98,"b":41},"_contentSize":{"__type__":"cc.Size","width":250,"height":99},"_trs":{"__type__":"TypedArray","ctor":"Float64Array","array":[0,0,0,0,0,0,1,1,1,1]}},{"__type__":"cc.Sprite","node":{"__id__":34},"_materials":[{"__uuid__":"ecpdLyjvZBwrvm+cedCcQy"}],"_spriteFrame":{"__uuid__":"41D7kWhyFGY7q4NDlzkazn"},"_sizeMode":0},{"__type__":"cc.Node","_name":"lab","_parent":{"__id__":33},"_components":[{"__type__":"cc.Label","node":{"__id__":36},"_materials":[{"__uuid__":"ecpdLyjvZBwrvm+cedCcQy"}],"_useOriginalSize":false,"_string":"上周","_N$string":"上周","_fontSize":44,"_lineHeight":44,"_N$horizontalAlign":1,"_N$verticalAlign":1}],"_prefab":{"__type__":"cc.PrefabInfo","root":{"__id__":1},"asset":{"__uuid__":"b0vDWc0FpBrqXtpimJc21n"},"fileId":"5dAD627shDxYYDp5z7SH/E"},"_color":{"__type__":"cc.Color","r":253,"g":210,"b":170},"_contentSize":{"__type__":"cc.Size","width":88,"height":55.44},"_trs":{"__type__":"TypedArray","ctor":"Float64Array","array":[0,0,0,0,0,0,1,1,1,1]}},{"__type__":"cc.Node","_name":"thisMonth","_parent":{"__id__":20},"_children":[{"__id__":38},{"__id__":40}],"_components":[{"__type__":"cc.Toggle","node":{"__id__":37},"_N$isChecked":false,"checkMark":{"__id__":39},"checkEvents":[{"__type__":"cc.ClickEvent","target":{"__id__":1},"_componentId":"34bedzKGa9EF6IpSJuhmFS/","handler":"onClickTime","customEventData":"本月"}]}],"_prefab":{"__type__":"cc.PrefabInfo","root":{"__id__":1},"asset":{"__uuid__":"b0vDWc0FpBrqXtpimJc21n"},"fileId":"9bKj4JQthFOoqxdR2Z1BoA"},"_contentSize":{"__type__":"cc.Size","width":368,"height":99},"_trs":{"__type__":"TypedArray","ctor":"Float64Array","array":[552,0,0,0,0,0,1,1,1,1]}},{"__type__":"cc.Node","_name":"bg","_parent":{"__id__":37},"_active":false,"_components":[{"__id__":39}],"_prefab":{"__type__":"cc.PrefabInfo","root":{"__id__":1},"asset":{"__uuid__":"b0vDWc0FpBrqXtpimJc21n"},"fileId":"09KRHzbNBJLJiWStQaYE2F"},"_color":{"__type__":"cc.Color","r":156,"g":98,"b":41},"_contentSize":{"__type__":"cc.Size","width":250,"height":99},"_trs":{"__type__":"TypedArray","ctor":"Float64Array","array":[0,0,0,0,0,0,1,1,1,1]}},{"__type__":"cc.Sprite","node":{"__id__":38},"_materials":[{"__uuid__":"ecpdLyjvZBwrvm+cedCcQy"}],"_spriteFrame":{"__uuid__":"41D7kWhyFGY7q4NDlzkazn"},"_sizeMode":0},{"__type__":"cc.Node","_name":"lab","_parent":{"__id__":37},"_components":[{"__type__":"cc.Label","node":{"__id__":40},"_materials":[{"__uuid__":"ecpdLyjvZBwrvm+cedCcQy"}],"_useOriginalSize":false,"_string":"本月","_N$string":"本月","_fontSize":44,"_lineHeight":44,"_N$horizontalAlign":1,"_N$verticalAlign":1}],"_prefab":{"__type__":"cc.PrefabInfo","root":{"__id__":1},"asset":{"__uuid__":"b0vDWc0FpBrqXtpimJc21n"},"fileId":"3fjkM0lGVL17SopBRAP0Rt"},"_color":{"__type__":"cc.Color","r":253,"g":210,"b":170},"_contentSize":{"__type__":"cc.Size","width":88,"height":55.44},"_trs":{"__type__":"TypedArray","ctor":"Float64Array","array":[0,0,0,0,0,0,1,1,1,1]}},{"__type__":"cc.Node","_name":"lastMonth","_parent":{"__id__":20},"_children":[{"__id__":42},{"__id__":44}],"_components":[{"__type__":"cc.Toggle","node":{"__id__":41},"_N$isChecked":false,"checkMark":{"__id__":43},"checkEvents":[{"__type__":"cc.ClickEvent","target":{"__id__":1},"_componentId":"34bedzKGa9EF6IpSJuhmFS/","handler":"onClickTime","customEventData":"上月"}]}],"_prefab":{"__type__":"cc.PrefabInfo","root":{"__id__":1},"asset":{"__uuid__":"b0vDWc0FpBrqXtpimJc21n"},"fileId":"21h8VawTNE7Icoja3spYLT"},"_contentSize":{"__type__":"cc.Size","width":368,"height":99},"_trs":{"__type__":"TypedArray","ctor":"Float64Array","array":[920,0,0,0,0,0,1,1,1,1]}},{"__type__":"cc.Node","_name":"bg","_parent":{"__id__":41},"_active":false,"_components":[{"__id__":43}],"_prefab":{"__type__":"cc.PrefabInfo","root":{"__id__":1},"asset":{"__uuid__":"b0vDWc0FpBrqXtpimJc21n"},"fileId":"03Eb0r5clGS607z24piNru"},"_color":{"__type__":"cc.Color","r":156,"g":98,"b":41},"_contentSize":{"__type__":"cc.Size","width":250,"height":99},"_trs":{"__type__":"TypedArray","ctor":"Float64Array","array":[0,0,0,0,0,0,1,1,1,1]}},{"__type__":"cc.Sprite","node":{"__id__":42},"_materials":[{"__uuid__":"ecpdLyjvZBwrvm+cedCcQy"}],"_spriteFrame":{"__uuid__":"41D7kWhyFGY7q4NDlzkazn"},"_sizeMode":0},{"__type__":"cc.Node","_name":"lab","_parent":{"__id__":41},"_components":[{"__type__":"cc.Label","node":{"__id__":44},"_materials":[{"__uuid__":"ecpdLyjvZBwrvm+cedCcQy"}],"_useOriginalSize":false,"_string":"上月","_N$string":"上月","_fontSize":44,"_lineHeight":44,"_N$horizontalAlign":1,"_N$verticalAlign":1}],"_prefab":{"__type__":"cc.PrefabInfo","root":{"__id__":1},"asset":{"__uuid__":"b0vDWc0FpBrqXtpimJc21n"},"fileId":"13wet8JMpCz59qLsMi3fgc"},"_color":{"__type__":"cc.Color","r":253,"g":210,"b":170},"_contentSize":{"__type__":"cc.Size","width":88,"height":55.44},"_trs":{"__type__":"TypedArray","ctor":"Float64Array","array":[0,0,0,0,0,0,1,1,1,1]}}],{"__type__":"cc.SpriteFrame","content":{"name":"noInfo","texture":"1ca2bc385","rect":[3,3,247,265],"offset":[0,0],"originalSize":[247,265],"capInsets":[0,0,0,0]}},{"__type__":"cc.SpriteFrame","content":{"name":"bg_top","texture":"126993316","rect":[93,45,30,30],"offset":[0,0],"originalSize":[30,30],"capInsets":[10,10,10,10]}}]